Metadata-Version: 1.1
Name: htmlcompressor
Version: 1.0.2
Summary: Compress HTML CSS and Java Script of a page.
Home-page: https://github.com/sxslex/htmlcompressor
Author: SleX
Author-email: sx.slex@gmail.com
License: UNKNOWN
Download-URL: https://github.com/sxslex/htmlcompressor/archive/v1.0.2.tar.gz
Keywords: html,css,javascript,compressor,minify
Platform: UNKNOWN
Classifier: License :: OSI Approved :: GNU General Public License (GPL)
Classifier: Natural Language :: English
Classifier: Operating System :: OS Independent
Classifier: Programming Language :: Python :: 2.6
Classifier: Programming Language :: Python :: 2.7
Classifier: Programming Language :: Python :: 3.3
Classifier: Programming Language :: Python :: 3.4
Classifier: Programming Language :: Python :: 3.5
Classifier: Programming Language :: Python :: 3.6
Classifier: Topic :: Software Development :: Libraries :: Python Modules
